humingbird/__init__.py
humingbird/resources/__init__.py
humingbird/resources/image.py
humingbird/resources/text.py
humingbird-0.5.1.dist-info/METADATA
humingbird-0.5.1.dist-info/WHEEL
humingbird-0.5.1.dist-info/top_level.txt
humingbird-0.5.1.dist-info/RECORD
