Metadata-Version: 2.1
Name: humingbird
Version: 0.5.1
Summary: Python SDK for Humingbird!
Home-page: UNKNOWN
License: MIT
Platform: UNKNOWN
Requires-Dist: Pillow (>=7.1)
Requires-Dist: transformers (>=4.19.2)
Requires-Dist: torch (>=1.11.0)
